CHANGELOG.md
CODE_OF_CONDUCT.md
CONTRIBUTING.md
LICENSE
README.md
setup.cfg
setup.py
asciinema/__init__.py
asciinema/__main__.py
asciinema/api.py
asciinema/async_worker.py
asciinema/config.py
asciinema/http_adapter.py
asciinema/notifier.py
asciinema/player.py
asciinema/pty.py
asciinema/recorder.py
asciinema/term.py
asciinema/urllib_http_adapter.py
asciinema/asciicast/__init__.py
asciinema/asciicast/events.py
asciinema/asciicast/raw.py
asciinema/asciicast/v1.py
asciinema/asciicast/v2.py
asciinema/commands/__init__.py
asciinema/commands/auth.py
asciinema/commands/cat.py
asciinema/commands/command.py
asciinema/commands/play.py
asciinema/commands/record.py
asciinema/commands/upload.py
asciinema/data/icon-256x256.png
asciinema2.egg-info/PKG-INFO
asciinema2.egg-info/SOURCES.txt
asciinema2.egg-info/dependency_links.txt
asciinema2.egg-info/entry_points.txt
asciinema2.egg-info/top_level.txt
doc/asciicast-v1.md
doc/asciicast-v2.md
man/asciinema.1